huedominance/__init__.py
huedominance/__main__.py
huedominance/gcc.py
huedominance/hrdi.py
huedominance-0.1.2.dist-info/LICENSE
huedominance-0.1.2.dist-info/WHEEL
huedominance-0.1.2.dist-info/METADATA
huedominance-0.1.2.dist-info/RECORD
