Metadata-Version: 2.1
Name: huedominance
Version: 0.1.2
Summary: Hue Range Dominance Index (HRDI) algorithm
Keywords: plant phenology,phenocam,vegetation
Author-email: Oleg Mirzov <oleg.mirzov@nateko.lu.se>
Requires-Python: >=3.5
Classifier: License :: OSI Approved :: GNU General Public License v3 or later (GPLv3+)
Requires-Dist: Pillow
Requires-Dist: numpy
Project-URL: Source, https://github.com/ICOS-Carbon-Portal/data/tree/master/src/main/python/huedominance
